zenutils/__init__.py
zenutils/base64utils.py
zenutils/baseutils.py
zenutils/cacheutils.py
zenutils/cipherutils.py
zenutils/dateutils.py
zenutils/dictutils.py
zenutils/errorutils.py
zenutils/fsutils.py
zenutils/funcutils.py
zenutils/hashutils.py
zenutils/httputils.py
zenutils/importutils.py
zenutils/jsonutils.py
zenutils/listutils.py
zenutils/logutils.py
zenutils/nameutils.py
zenutils/numericutils.py
zenutils/packutils.py
zenutils/perfutils.py
zenutils/randomutils.py
zenutils/serviceutils.py
zenutils/sixutils.py
zenutils/socketserverutils.py
zenutils/strutils.py
zenutils/sysutils.py
zenutils/threadutils.py
zenutils/treeutils.py
zenutils/typingutils.py
zenutils/xmlrpcutils.py
zenutils-0.5.5.dist-info/LICENSE
zenutils-0.5.5.dist-info/METADATA
zenutils-0.5.5.dist-info/WHEEL
zenutils-0.5.5.dist-info/top_level.txt
zenutils-0.5.5.dist-info/RECORD
