Metadata-Version: 2.1
Name: zenutils
Version: 0.5.5
Summary: Collection of simple utils.
Author: Xin HaoJia
Maintainer: Xin HaoJia
License: MIT
Keywords: zenutils
Classifier: Development Status :: 5 - Production/Stable
Classifier: Intended Audience :: Developers
Classifier: Topic :: Software Development :: Libraries :: Python Modules
Classifier: License :: OSI Approved :: MIT License
Classifier: Programming Language :: Python :: 3
Classifier: Programming Language :: Python :: 3 :: Only
License-File: LICENSE
Requires-Dist: inspect2 ~=0.1.2
